runtests.py
joinfield/__init__.py
joinfield/joinfield.py
django_joinfield-0.2.1.dist-info/METADATA
django_joinfield-0.2.1.dist-info/WHEEL
django_joinfield-0.2.1.dist-info/licenses/LICENSE
django_joinfield-0.2.1.dist-info/RECORD
