Metadata-Version: 2.1
Name: django-joinfield
Version: 0.2.1
Summary: A field type for Django models that allows joins to a related model without a foreign key.
Project-URL: Homepage, https://github.com/martsberger/django-joinfield
Project-URL: Download, https://github.com/martsberger/django-joinfield/archive/0.2.1.tar.gz
Author-email: Brad Martsberger <bradley.marts@gmail.com>
License-File: LICENSE
Classifier: License :: OSI Approved :: MIT License
Classifier: Operating System :: OS Independent
Classifier: Programming Language :: Python :: 3
Requires-Python: >=3.8
Requires-Dist: django>=3.2
